env_resolver/__init__.py
env_resolver/main.py
env_resolver-0.1.7.dist-info/WHEEL
env_resolver-0.1.7.dist-info/METADATA
env_resolver-0.1.7.dist-info/RECORD
