Metadata-Version: 2.1
Name: env-resolver
Version: 0.1.7
Summary: A utility for resolving ssm parameters and secretsmanager secrets
Home-page: https://github.com/wulfmann/env-resolver/tree/master/python
License: MIT
Keywords: ssm,secretsmanager,aws,environment,utility
Author: Joe Snell
Author-email: joepsnell@gmail.com
Requires-Python: >=3.7
Classifier: License :: OSI Approved :: MIT License
Classifier: Programming Language :: Python :: 3
Classifier: Programming Language :: Python :: 3.7
Classifier: Programming Language :: Python :: 3.8
Project-URL: Repository, https://github.com/wulfmann/env-resolver/tree/master/python
